LICENSE.txt
MANIFEST.in
README.rst
setup.cfg
setup.py
cliwaka/__init__.py
cliwaka/__main__.py
cliwaka/cli.py
cliwaka/config.py
cliwaka/core.py
cliwaka/output.py
cliwaka.egg-info/PKG-INFO
cliwaka.egg-info/SOURCES.txt
cliwaka.egg-info/dependency_links.txt
cliwaka.egg-info/entry_points.txt
cliwaka.egg-info/requires.txt
cliwaka.egg-info/top_level.txt