Metadata-Version: 1.1
Name: cliwaka
Version: 0.1.1
Summary: Cliwaka is an interactive command line utility for wakatime.com
Home-page: https://github.com/shashankgroovy/cliwaka
Author: Shashank Srivastav
Author-email: shashankgrovy@gmail.com
License: GPLv3
Download-URL: https://github.com/shashankgroovy/cliwaka/archive/master.zip
Keywords: wakatime cli tool
Platform: UNKNOWN
Classifier: Development Status :: 3 - Alpha
Classifier: License :: OSI Approved :: GNU General Public License v3 (GPLv3)
Classifier: Programming Language :: Python :: 2.7
Classifier: Programming Language :: Python :: 3
Classifier: Topic :: Utilities
